pdf_anonymizer_cli/__init__.py
pdf_anonymizer_cli/cli.py
pdf_anonymizer_cli/main.py
pdf_anonymizer_cli-0.3.2.dist-info/METADATA
pdf_anonymizer_cli-0.3.2.dist-info/WHEEL
pdf_anonymizer_cli-0.3.2.dist-info/entry_points.txt
pdf_anonymizer_cli-0.3.2.dist-info/top_level.txt
pdf_anonymizer_cli-0.3.2.dist-info/RECORD
