Metadata-Version: 2.4
Name: pdf-anonymizer-cli
Version: 0.3.2
Summary: CLI for a tool to anonymize PDF, Markdown, and plain text files using LLMs.
Author-email: Leonid Ganeline <leo.gan.57@gmail.com>
License: MIT
Project-URL: repository, https://github.com/leo-gan/anonymizer
Requires-Python: >=3.10
Requires-Dist: typer
Requires-Dist: rich
Requires-Dist: pdf-anonymizer-core
